kivy_chess_board/__init__.py
kivy_chess_board/_chess_button.py
kivy_chess_board/_highlight_square.py
kivy_chess_board/arrows.py
kivy_chess_board/assets/B.png
kivy_chess_board/assets/K.png
kivy_chess_board/assets/N.png
kivy_chess_board/assets/P.png
kivy_chess_board/assets/Q.png
kivy_chess_board/assets/R.png
kivy_chess_board/assets/b_black.png
kivy_chess_board/assets/board.png
kivy_chess_board/assets/board_inverted.png
kivy_chess_board/assets/k_black.png
kivy_chess_board/assets/n_black.png
kivy_chess_board/assets/p_black.png
kivy_chess_board/assets/q_black.png
kivy_chess_board/assets/r_black.png
kivy_chess_board/assets.py
kivy_chess_board/chess_board.kv
kivy_chess_board/chess_board.py
kivy_chess_board/nop.py
kivy_chess_board/type.py
kivy_chess_board-1.0.2.dist-info/WHEEL
kivy_chess_board-1.0.2.dist-info/METADATA
kivy_chess_board-1.0.2.dist-info/RECORD
