Metadata-Version: 2.4
Name: kivy-chess-board
Version: 1.0.2
Summary: Provides a chess board as a kivy widget.
Keywords: chess
Author: Moritz R. Schäfer
Author-email: Moritz R. Schäfer <moritz.schaefer-f91@rub.de>
License-Expression: GPL-3.0-or-later
Requires-Dist: chess>=1.11.1
Requires-Dist: kivy>=2.3.1
Requires-Dist: pdoc ; extra == 'docs'
Maintainer: Moritz R. Schäfer
Maintainer-email: Moritz R. Schäfer <moritz.schaefer-f91@rub.de>
Requires-Python: >=3.10, <3.14
Project-URL: Repository, https://gitlab.com/M0M097/kivy-chess-board
Project-URL: Documentation, https://kivy-chess-board-ebce1f.gitlab.io/
Project-URL: Issues, https://gitlab.com/M0M097/kivy-chess-board/-/issues
Provides-Extra: docs
